elidetext/__init__.py
elidetext/elidetext.py
elide_text-0.0.1.dist-info/LICENSE
elide_text-0.0.1.dist-info/METADATA
elide_text-0.0.1.dist-info/WHEEL
elide_text-0.0.1.dist-info/top_level.txt
elide_text-0.0.1.dist-info/RECORD
